<?xml version="1.0" encoding="UTF-8"?>
<!-- Copyright 2004 Sun Microsystems, Inc.  All rights reserved.  You may not modify, use, reproduce, or distribute this software except in compliance with the terms of the License at: 
 http://adventurebuilder.dev.java.net/LICENSE.txt
 $Id: sun-ejb-jar.xml,v 1.9 2005/11/12 00:27:31 smitha Exp $ -->
<!DOCTYPE sun-ejb-jar PUBLIC "-//Sun Microsystems, Inc.//DTD Application Server
8.0 EJB 2.1//EN" "http://www.sun.com/software/appserver/dtds/sun-ejb-jar_2_1-0.dtd">
<sun-ejb-jar>
  <enterprise-beans>
    <ejb>
      <ejb-name>CheckoutNotificationEjb</ejb-name>
      <jndi-name>queue/GoogleCheckoutInbox</jndi-name>
      <mdb-connection-factory>
        <jndi-name>queue/QueueConnectionFactory</jndi-name>
      </mdb-connection-factory>
    </ejb>
  </enterprise-beans>
</sun-ejb-jar>
